{"elementor_version":"3.0.15","woof_try_ajax":"1","woof_filter_btn_txt":"Apply","woof_reset_btn_txt":"Clear filters","woof_settings":{"items_order":"by_featured,by_onsales,product_visibility,product_cat,pa_color,by_price,pa_height,pa_length,product_tag,pa_material,pa_size,pa_weight,pa_width,translation_priority","by_featured":{"show":"0"},"by_onsales":{"show":"0"},"tax_type":{"product_visibility":"slider","product_cat":"checkbox","pa_color":"color","pa_height":"radio","pa_length":"radio","product_tag":"label","pa_material":"image","pa_size":"label","pa_weight":"radio","pa_width":"radio","translation_priority":"radio","pa_lamp-style":"radio"},"excluded_terms":{"product_visibility":"","product_cat":"","pa_color":"","pa_height":"","pa_length":"","product_tag":"","pa_material":"","pa_size":"","pa_weight":"","pa_width":"","translation_priority":"","pa_lamp-style":""},"tax_block_height":{"product_visibility":"0","product_cat":"0","pa_color":"0","pa_height":"0","pa_length":"0","product_tag":"0","pa_material":"0","pa_size":"0","pa_weight":"0","pa_width":"0","translation_priority":"0","pa_lamp-style":"0"},"show_title_label":{"product_visibility":"1","product_cat":"1","pa_color":"1","pa_height":"0","pa_length":"0","product_tag":"1","pa_material":"0","pa_size":"1","pa_weight":"1","pa_width":"0","translation_priority":"0","pa_lamp-style":"0"},"show_toggle_button":{"product_visibility":"0","product_cat":"0","pa_color":"0","pa_height":"0","pa_length":"0","product_tag":"0","pa_material":"0","pa_size":"0","pa_weight":"0","pa_width":"0","translation_priority":"0","pa_lamp-style":"0"},"tooltip_text":{"product_visibility":"","product_cat":"","pa_color":"","pa_height":"","pa_length":"","product_tag":"","pa_material":"","pa_size":"","pa_weight":"","pa_width":"","translation_priority":"","pa_lamp-style":""},"dispay_in_row":{"product_visibility":"0","product_cat":"0","pa_color":"0","pa_height":"0","pa_length":"0","product_tag":"0","pa_material":"0","pa_size":"0","pa_weight":"0","pa_width":"0","translation_priority":"0","pa_lamp-style":"0"},"orderby":{"product_visibility":"-1","product_cat":"-1","pa_color":"-1","pa_height":"-1","pa_length":"-1","product_tag":"-1","pa_material":"-1","pa_size":"-1","pa_weight":"-1","pa_width":"-1","translation_priority":"-1","pa_lamp-style":"-1"},"order":{"product_visibility":"ASC","product_cat":"ASC","pa_color":"ASC","pa_height":"ASC","pa_length":"ASC","product_tag":"ASC","pa_material":"ASC","pa_size":"ASC","pa_weight":"ASC","pa_width":"ASC","translation_priority":"ASC","pa_lamp-style":"ASC"},"comparison_logic":{"product_visibility":"OR","product_cat":"OR","pa_color":"OR","pa_height":"OR","pa_length":"OR","product_tag":"OR","pa_material":"OR","pa_size":"OR","pa_weight":"OR","pa_width":"OR","translation_priority":"OR","pa_lamp-style":"OR"},"custom_tax_label":{"product_visibility":"","product_cat":"","pa_color":"","pa_height":"","pa_length":"","product_tag":"","pa_material":"","pa_size":"","pa_weight":"","pa_width":"","translation_priority":"","pa_lamp-style":""},"not_toggled_terms_count":{"product_visibility":"","product_cat":"","pa_color":"","pa_height":"","pa_length":"","product_tag":"","pa_material":"","pa_size":"","pa_weight":"","pa_width":"","translation_priority":"","pa_lamp-style":""},"show_tooltip":{"product_visibility":"0","product_cat":"0","pa_color":"1","pa_height":"0","pa_length":"0","product_tag":"0","pa_material":"0","pa_size":"0","pa_weight":"0","pa_width":"0","translation_priority":"0","pa_lamp-style":"0"},"show_title":{"product_visibility":"0","product_cat":"0","pa_color":"0","pa_height":"0","pa_length":"0","product_tag":"0","pa_material":"0","pa_size":"0","pa_weight":"0","pa_width":"0","translation_priority":"0","pa_lamp-style":"0"},"as_radio":{"product_visibility":"0","product_cat":"0","pa_color":"0","pa_height":"0","pa_length":"0","product_tag":"0","pa_material":"0","pa_size":"0","pa_weight":"0","pa_width":"0","translation_priority":"0","pa_lamp-style":"0"},"select_radio_check_type":{"product_visibility":"0","product_cat":"0","pa_color":"0","pa_height":"0","pa_length":"0","product_tag":"0","pa_material":"0","pa_size":"0","pa_weight":"0","pa_width":"0","translation_priority":"0","pa_lamp-style":"0"},"select_radio_check_height":{"product_visibility":"0","product_cat":"0","pa_color":"0","pa_height":"0","pa_length":"0","product_tag":"0","pa_material":"0","pa_size":"0","pa_weight":"0","pa_width":"0","translation_priority":"0","pa_lamp-style":"0"},"slider_dynamic_recount":{"product_visibility":"0","product_cat":"0","pa_color":"0","pa_height":"0","pa_length":"0","product_tag":"0","pa_material":"0","pa_size":"0","pa_weight":"0","pa_width":"0","translation_priority":"0","pa_lamp-style":"0"},"slider_grid_step":{"product_visibility":"0","product_cat":"0","pa_color":"0","pa_height":"0","pa_length":"0","product_tag":"0","pa_material":"0","pa_size":"0","pa_weight":"0","pa_width":"0","translation_priority":"0","pa_lamp-style":"0"},"tax":{"product_cat":"1","pa_color":"1","product_tag":"1","pa_material":"1","pa_weight":"1"},"color":{"pa_color":{"beige":"#f9f0e0","beige-caro":"#bfbfbf","black":"#000000","blue":"#1e73be","blue-beige":"#769cbf","brown":"#8e5936","green":"#81d742","grey":"#c9c9c9","grey-blue":"#a4b2bf","grey-yellow":"#ededc9","orange":"#f98639","red":"#dd3333","violet":"#a466e2","white":"#ffffff","yellow":"#eeee22"}},"color_img":{"pa_color":{"beige":"","beige-caro":"","black":"","blue":"","blue-beige":"","brown":"","green":"","grey":"","grey-blue":"","grey-yellow":"","orange":"","red":"","violet":"","white":"","yellow":""}},"by_price":{"show":"3","tooltip_text":"","show_button":"1","title_text":"Filter by price","show_toggle_button":"0","ranges":"0-50,51-100,101-150","first_option_text":"Drop-down price filter first option text","ion_slider_step":"2","price_tax":""},"images_term_107":{"image_url":"","image_styles":"width: 100px;\r\nheight:50px;\r\nmargin: 0 3px 3px 0;\r\nbackground-size: 100% 100%;\r\nbackground-clip: content-box;\r\nborder: 2px solid #e2e6e7;\r\npadding: 2px;\r\ncolor: #292f38;\r\nfont-size: 0;\r\ntext-align: center;\r\ncursor: pointer;\r\n-webkit-border-radius: 4px;\r\nborder-radius: 4px;\r\n-webkit-transition: border-color .35s ease;\r\ntransition: border-color .35s ease;"},"images_term_51":{"image_url":"","image_styles":"width: 100px;\r\nheight:50px;\r\nmargin: 0 3px 3px 0;\r\nbackground-size: 100% 100%;\r\nbackground-clip: content-box;\r\nborder: 2px solid #e2e6e7;\r\npadding: 2px;\r\ncolor: #292f38;\r\nfont-size: 0;\r\ntext-align: center;\r\ncursor: pointer;\r\n-webkit-border-radius: 4px;\r\nborder-radius: 4px;\r\n-webkit-transition: border-color .35s ease;\r\ntransition: border-color .35s ease;"},"images_term_108":{"image_url":"","image_styles":"width: 100px;\r\nheight:50px;\r\nmargin: 0 3px 3px 0;\r\nbackground-size: 100% 100%;\r\nbackground-clip: content-box;\r\nborder: 2px solid #e2e6e7;\r\npadding: 2px;\r\ncolor: #292f38;\r\nfont-size: 0;\r\ntext-align: center;\r\ncursor: pointer;\r\n-webkit-border-radius: 4px;\r\nborder-radius: 4px;\r\n-webkit-transition: border-color .35s ease;\r\ntransition: border-color .35s ease;"},"images_term_52":{"image_url":"","image_styles":"width: 100px;\r\nheight:50px;\r\nmargin: 0 3px 3px 0;\r\nbackground-size: 100% 100%;\r\nbackground-clip: content-box;\r\nborder: 2px solid #e2e6e7;\r\npadding: 2px;\r\ncolor: #292f38;\r\nfont-size: 0;\r\ntext-align: center;\r\ncursor: pointer;\r\n-webkit-border-radius: 4px;\r\nborder-radius: 4px;\r\n-webkit-transition: border-color .35s ease;\r\ntransition: border-color .35s ease;"},"icheck_skin":"square_aero","overlay_skin":"default","overlay_skin_bg_img":"","plainoverlay_color":"","default_overlay_skin_word":"Loading..","use_chosen":"1","use_beauty_scroll":"1","ion_slider_skin":"skinModern","use_tooltip":"0","woof_tooltip_img":"","woof_auto_hide_button_img":"","woof_auto_hide_button_txt":"","woof_auto_subcats_plus_img":"","woof_auto_subcats_minus_img":"","toggle_type":"text","toggle_opened_text":"","toggle_closed_text":"","toggle_opened_image":"","toggle_closed_image":"","custom_front_css":"","custom_css_code":"","js_after_ajax_done":"","init_only_on_reverse":"0","init_only_on":"","wpml_tax_labels":"","swoof_search_slug":"","per_page":"0","optimize_js_files":"0","override_no_products":"","show_images_by_attr_show":"0","hide_terms_count_txt":"0","listen_catalog_visibility":"1","disable_swoof_influence":"0","cache_count_data":"0","cache_terms":"0","show_woof_edit_view":"0","custom_extensions_path":"","result_count_redraw":"","order_dropdown_redraw":"","per_page_redraw":"","meta_filter":{"__META_KEY__":{"meta_key":"__META_KEY__","title":"__TITLE__","search_view":"slider","options":"","type":"NUMERIC"}},"activated_extensions":["2e8b771b8f6ee8300323e8d507b79b18","89d1fe7408907abf1f9cd0babaabc621","92fe22ed6bb9f2d200b52ad99b1af644","fb5128813d6a2d24bfb6c89d12d4dbb3","884cdb47a7050888afa7379f69861a13","c053bf072ad2368583f863d2d720295e","69f031349b43a731d27ebc467c8f8536","c4aaeaad95843980aefb612b76ce7a2c","777daeaac6214837cdede4e27e993892"]},"_elementor_installed_time":"1590654103","elementor_scheme_color":{"1":"#6ec1e4","2":"#54595f","3":"#7a7a7a","4":"#61ce70"},"elementor_scheme_typography":{"1":{"font_family":"Roboto","font_weight":"600"},"2":{"font_family":"Roboto Slab","font_weight":"400"},"3":{"font_family":"Roboto","font_weight":"400"},"4":{"font_family":"Roboto","font_weight":"500"}},"elementor_active_kit":"6754","elementor_library_category_children":[],"elementor_scheme_color-picker":{"1":"#6ec1e4","2":"#54595f","3":"#7a7a7a","4":"#61ce70","5":"#4054b2","6":"#23a455","7":"#000","8":"#fff"},"elementor_unfiltered_files_upload":"1","_elementor_general_settings":{"default_generic_fonts":"Sans-serif","container_width":"1440","global_image_lightbox":"yes","space_between_widgets":"30"},"_elementor_settings_update_time":"1602831792","elementor_cpt_support":["post","page","product","fmtpl_blocks"],"elementor_disable_color_schemes":"","elementor_disable_typography_schemes":"","elementor_allow_tracking":"no","elementor_default_generic_fonts":"Sans-serif","elementor_container_width":"1440","elementor_space_between_widgets":"0","elementor_stretched_section_container":"","elementor_page_title_selector":"","elementor_viewport_lg":"","elementor_viewport_md":"","elementor_global_image_lightbox":"","elementor_css_print_method":"external","elementor_editor_break_lines":"","elementor_enable_unfiltered_files_upload":"","elementor_load_fa4_shim":"","_elementor_editor_upgrade_notice_dismissed":"1602492679","elementor_pro_version":"2.8.4","widget_elementor-library":{"_multiwidget":1},"_elementor_pro_installed_time":"1597390170","elementor_custom_icon_sets_config":[],"elementor_fonts_manager_font_types":[],"elementor_fonts_manager_fonts":[],"elementor_install_history":{"3.0.2":1598519084,"3.0.3":1598587734,"3.0.4":1598838960,"3.0.5":1598923889,"3.0.6":1599447337,"3.0.7":1599721526,"3.0.8.1":1600306376,"3.0.9":1600392441,"3.0.11":1601622540,"3.0.12":1603242695,"3.0.13":1604629860,"3.0.14":1607304490,"3.0.15":1608565857},"elementor_notice":"","elementor_optimized_dom_output":"","elementor_tracker_notice":"1","elementor_clear_cache":"","elementor_reset_api_data":"","elementor_enable_inspector":"enable","elementor_replace_url":"","elementor_rollback":"","elementor_re_migrate_globals_separator":"","elementor_re_migrate_globals":"","elementor_beta":"no","elementor_maintenance_mode_mode":"","elementor_maintenance_mode_exclude_mode":"logged_in","elementor_maintenance_mode_exclude_roles":[],"elementor_maintenance_mode_template_id":"","elementor_safe_mode":"","_elementor_global_css":{"time":1608565858,"fonts":[],"icons":[],"dynamic_elements_ids":[],"status":"file","0":false},"dbem_credits":0,"woocommerce_cart_redirect_after_add":"yes","woocommerce_enable_ajax_add_to_cart":"no"}